vardxg/__init__.py
vardxg/aurora.py
vardxg/magic.py
vardxg/protobuf.py
vardxg/xor.py
vardxg-1.1.2.dist-info/METADATA
vardxg-1.1.2.dist-info/WHEEL
vardxg-1.1.2.dist-info/top_level.txt
vardxg-1.1.2.dist-info/RECORD
