Metadata-Version: 2.1
Name: vardxg
Version: 1.1.2
Summary: My Useful Utils Lib
Author: vardxg
Author-email: <vardxgdev@gmail.com>
Keywords: python,dev,free,encrypt,tools
Classifier: Development Status :: 1 - Planning
Classifier: Intended Audience :: Developers
Classifier: Programming Language :: Python :: 3
Classifier: Operating System :: Unix
Classifier: Operating System :: MacOS :: MacOS X
Classifier: Operating System :: Microsoft :: Windows
Requires-Dist: requests
